CHANGES.txt
LICENSE.txt
MANIFEST.in
README.txt
setup.py
js/__init__.py
js.jquery_mailcheck.egg-info/PKG-INFO
js.jquery_mailcheck.egg-info/SOURCES.txt
js.jquery_mailcheck.egg-info/dependency_links.txt
js.jquery_mailcheck.egg-info/entry_points.txt
js.jquery_mailcheck.egg-info/namespace_packages.txt
js.jquery_mailcheck.egg-info/not-zip-safe
js.jquery_mailcheck.egg-info/requires.txt
js.jquery_mailcheck.egg-info/top_level.txt
js/jquery_mailcheck/__init__.py
js/jquery_mailcheck/test_jquery_mailcheck.txt
js/jquery_mailcheck/resources/jquery.mailcheck.js
js/jquery_mailcheck/resources/jquery.mailcheck.min.js