Metadata-Version: 1.0
Name: js.jquery-mailcheck
Version: 1.0.1
Summary: Fanstatic packaging of jQuery mailcheck
Home-page: UNKNOWN
Author: Fanstatic Developers
Author-email: fanstatic@googlegroups.com
License: BSD
Platform: UNKNOWN
